umakit/__init__.py
umakit/logtool.py
umakit-0.1.1.dist-info/LICENSE
umakit-0.1.1.dist-info/METADATA
umakit-0.1.1.dist-info/WHEEL
umakit-0.1.1.dist-info/top_level.txt
umakit-0.1.1.dist-info/RECORD
