Metadata-Version: 2.1
Name: umakit
Version: 0.1.1
Summary: Paket python buatan uma
Home-page: https://github.com/taruma/umakit
Author: Taruma
Author-email: hi@taruma.info
License: MIT
Platform: UNKNOWN
Classifier: License :: OSI Approved :: MIT License
Classifier: Programming Language :: Python
Classifier: Programming Language :: Python :: 3
Classifier: Programming Language :: Python :: 3.6
Requires-Python: >=3.6.0
